libgriffig.a
_griffig.cpython-37m-x86_64-linux-gnu.so
pyaffx.cpython-37m-x86_64-linux-gnu.so
libaffx.a
griffig/__init__.py
griffig/griffig.py
griffig/infer/inference_semantic.py
griffig/infer/inference_planar.py
griffig/infer/inference_base.py
griffig/infer/__init__.py
griffig/infer/inference.py
griffig/infer/inference_actor_critic.py
griffig/infer/selection.py
griffig/action/converter.py
griffig/action/__init__.py
griffig/action/checker.py
griffig/utility/heatmap.py
griffig/utility/__init__.py
griffig/utility/model_library.py
griffig/utility/image.py
griffig/utility/model_data.py
griffig/utility/box_finder.py
griffig-0.0.3.dist-info/LICENSE
griffig-0.0.3.dist-info/METADATA
griffig-0.0.3.dist-info/top_level.txt
griffig-0.0.3.dist-info/RECORD
griffig-0.0.3.dist-info/WHEEL
griffig.libs/libOpenGL-8a3d9fca.so.0.0.0
griffig.libs/libXau-b2e5323c.so.6.0.0
griffig.libs/libopencv_core-ec1e0024.so.4.5.2
griffig.libs/libX11-xcb-ad1f1f15.so.1.0.0
griffig.libs/libGLU-8496b5fb.so.1.3.1
griffig.libs/libgbm-96f6e683.so.1.0.0
griffig.libs/libxcb-shape-893f3868.so.0.0.0
griffig.libs/libEGL-b7f9cbd0.so.1.0.0
griffig.libs/libGLdispatch-a6a5cd8b.so.0.0.0
griffig.libs/libxcb-render-b2bf401c.so.0.0.0
griffig.libs/libxcb-xfixes-6523fc53.so.0.0.0
griffig.libs/libselinux-d72a37e2.so.1
griffig.libs/libxcb-dri2-21d0e1c6.so.0.0.0
griffig.libs/libdrm-d2c025d8.so.2.4.0
griffig.libs/libGLEW-f657e430.so.1.5.5
griffig.libs/libxcb-77222338.so.1.1.0
griffig.libs/libopencv_imgproc-c0306836.so.4.5.2
