Metadata-Version: 2.1
Name: griffig
Version: 0.0.3
Summary: Robotic Manipulation Learned from Imitation and Self-Supervision
Home-page: https://github.com/pantor/griffig
Author: Lars Berscheid
Author-email: lars.berscheid@kit.edu
License: LGPL
Keywords: robot,robotics,grasping,robot-learning
Platform: UNKNOWN
Classifier: Development Status :: 3 - Alpha
Classifier: Intended Audience :: Science/Research
Classifier: Topic :: Scientific/Engineering
Classifier: License :: OSI Approved :: GNU Lesser General Public License v3 (LGPLv3)
Classifier: Programming Language :: C++
Requires-Python: >=3.6
License-File: LICENSE
Requires-Dist: loguru
Requires-Dist: tensorflow (==2.4)
Requires-Dist: opencv-python
Requires-Dist: numpy
Requires-Dist: scipy (==1.5)
Requires-Dist: Pillow
